Metadata-Version: 2.1
Name: mysq
Version: 0.0.13
Summary: exam copy
Author: kaushal bhatol
Author-email: <kaushal@bhatol.com>
Keywords: exam
Classifier: Development Status :: 1 - Planning
Classifier: Intended Audience :: Developers
Classifier: Programming Language :: Python :: 3
Classifier: Operating System :: Unix
Classifier: Operating System :: MacOS :: MacOS X
Classifier: Operating System :: Microsoft :: Windows
Requires-Dist: requests
